righttyper/__init__.py
righttyper/__main__.py
righttyper/annotation_coverage.py
righttyper/ast_instrument.py
righttyper/generate_stubs.py
righttyper/loader.py
righttyper/options.py
righttyper/py.typed
righttyper/random_dict.py
righttyper/replace_dicts.py
righttyper/righttyper.py
righttyper/righttyper_alarm.py
righttyper/righttyper_process.py
righttyper/righttyper_runtime.py
righttyper/righttyper_tool.py
righttyper/righttyper_types.py
righttyper/righttyper_utils.py
righttyper/typeinfo.py
righttyper/unified_transformer.py
righttyper-0.1.0.dist-info/licenses/LICENSE
righttyper-0.1.0.dist-info/licenses/NOTICE
righttyper-0.1.0.dist-info/METADATA
righttyper-0.1.0.dist-info/WHEEL
righttyper-0.1.0.dist-info/entry_points.txt
righttyper-0.1.0.dist-info/top_level.txt
righttyper-0.1.0.dist-info/RECORD
