Metadata-Version: 2.4
Name: righttyper
Version: 0.1.0
Summary: A fast runtime type hint assistant for Python code.
Author-email: Emery Berger <emerydb@amazon.com>, Juan Altmayer Pizzorno <jpizzorno@umass.edu>
Classifier: Programming Language :: Python :: 3
Classifier: License :: OSI Approved :: MIT License
Classifier: Operating System :: OS Independent
Requires-Python: >=3.12
License-File: LICENSE
License-File: NOTICE
Requires-Dist: libcst>=1.2.0
Requires-Dist: click>=8.1.7
Requires-Dist: rich>=13.7.1
Requires-Dist: wcmatch>=10.0
Requires-Dist: typeshed_client
Provides-Extra: tests
Requires-Dist: pytest; extra == "tests"
Requires-Dist: mypy; extra == "tests"
Requires-Dist: numpy; extra == "tests"
Requires-Dist: ml_dtypes; extra == "tests"
Requires-Dist: jax; extra == "tests"
Requires-Dist: jaxtyping; extra == "tests"
Requires-Dist: torch; extra == "tests"
Provides-Extra: shapes
Requires-Dist: jaxtyping; extra == "shapes"
Dynamic: license-file
